.gitignore
CHANGES.txt
CONTRIBUTORS.txt
LICENSE.txt
README.txt
setup.cfg
setup.py
tox.ini
pyramid_pluggable_session/__init__.py
pyramid_pluggable_session/chain.py
pyramid_pluggable_session/file.py
pyramid_pluggable_session/interfaces.py
pyramid_pluggable_session/memory.py
pyramid_pluggable_session.egg-info/PKG-INFO
pyramid_pluggable_session.egg-info/SOURCES.txt
pyramid_pluggable_session.egg-info/dependency_links.txt
pyramid_pluggable_session.egg-info/not-zip-safe
pyramid_pluggable_session.egg-info/requires.txt
pyramid_pluggable_session.egg-info/top_level.txt